drf_actions/__init__.py
drf_actions/admin.py
drf_actions/app_settings.py
drf_actions/apps.py
drf_actions/migrations/0001_initial.py
drf_actions/migrations/0002_auto_20200618_1044.py
drf_actions/migrations/0003_auto_20210729_0724.py
drf_actions/migrations/__init__.py
drf_actions/models.py
drf_actions/serializers/__init__.py
drf_actions/serializers/event_journal.py
drf_actions/signals.py
drf_actions/tasks.py
drf_actions/urls.py
drf_actions/views/__init__.py
drf_actions/views/event_journal.py
drf_actions-0.3.0.dist-info/LICENSE
drf_actions-0.3.0.dist-info/WHEEL
drf_actions-0.3.0.dist-info/METADATA
drf_actions-0.3.0.dist-info/RECORD
